<?xml version="1.0" encoding="utf-8"?>
<odoo>
    <data>
        <!-- actions opening views on models rent vehicle -->
        <record model="ir.actions.act_window"
                id="vechicle_rental.action_window">
            <field name="name">Vehicle Rental</field>
            <field name="res_model">vehicle.rental</field>
            <field name="view_mode">kanban,tree,form</field>
            <field name="context">{"search_default_filter_by_available": 1}
            </field>
            <field name="help" type="html">
                <p class="o_view_nocontent_smiling_face">
                    Create a Vehicle rental
                </p>
            </field>
        </record>
        <!--        action opening views o model Rent Request-->
        <record id="vehicle_request" model="ir.actions.act_window">
            <field name="name">Rent Request</field>
            <field name="res_model">vehicle.request</field>
            <field name="view_mode">tree,kanban,form</field>
            <field name="help" type="html">
                <p class="o_view_nocontent_smiling_face">
                    Create a Vehicle rental Request
                </p>
            </field>
        </record>
        <!--        action for Report menu-->
        <!--        Vehicle Rent Report menu-->
        <record id="create_vehicle_rent_report" model="ir.actions.act_window">
            <field name="name">Vehicle Rental Report</field>
            <field name="res_model">vehicle.report</field>
            <field name="view_mode">form</field>
            <field name="view_id" ref="vehicle_rent_report"/>
            <field name="target">new</field>
        </record>

        <!--  Sequence menus that the listed order -->
<!--        main menu-->
        <menuitem id="vehicle_home" name="Vehicle Rental" sequence="1"/>
<!--        App menus -->
<!--        Rent Vehicle menu-->
        <menuitem id="vehicle" name="Rent Vehicles" parent="vehicle_home"
                  action="vechicle_rental.action_window" sequence="1"/>
<!--    Rent Request menu-->
        <menuitem id="request" name="Rent Request" parent="vehicle_home"
                  action="vehicle_request" sequence="2"/>
<!--        Report menu-->
        <menuitem id="vehicle_report" name="Reports" parent="vehicle_home"
                  sequence="3"/>
<!--        Vehicle Rent Report Sub menu-->
        <menuitem id="vehicle_rental_report" name="Vehicle Rental Report"
                  parent="vehicle_report"
                  action="create_vehicle_rent_report" sequence="1"/>
    </data>
</odoo>