<odoo>
    <data>
<!--        <record id="product_video_pos" model="ir.ui.view">-->
<!--            <field name="name">Product.qnt.pos</field>-->
<!--            <field name="model">product.template</field>-->
<!--            <field name="inherit_id"-->
<!--                   ref="product.product_template_only_form_view"/>-->
<!--            <field name="arch" type="xml">-->
<!--                <field name="l10n_in_hsn_description" position="after">-->
<!--                    <field name="sold_qty" invisible="True" group=-->
<!--                    "base.group_user"/>-->
<!--                    <field name="no_of_view" invisible="True" group=-->
<!--                    "base.group_user"/>-->
<!--                    <field name="top_selling" group=-->
<!--                    "base.group_user" invisible="True"/>-->
<!--                    <field name="most_visited" group=-->
<!--                    "base.group_user" invisible="True"/>-->
<!--                </field>-->
<!--            </field>-->
<!--        </record>-->
    </data>
</odoo>